robotframework_metrics/__init__.py
robotframework_metrics/dashboard_stats.py
robotframework_metrics/details.py
robotframework_metrics/keyword_results.py
robotframework_metrics/keyword_times.py
robotframework_metrics/robotmetrics.py
robotframework_metrics/runner.py
robotframework_metrics/suite_results.py
robotframework_metrics/test_results.py
robotframework_metrics/version.py
robotframework_metrics/templates/index.html
robotframework_metrics-3.7.0.dist-info/LICENSE
robotframework_metrics-3.7.0.dist-info/METADATA
robotframework_metrics-3.7.0.dist-info/WHEEL
robotframework_metrics-3.7.0.dist-info/entry_points.txt
robotframework_metrics-3.7.0.dist-info/top_level.txt
robotframework_metrics-3.7.0.dist-info/RECORD
