Metadata-Version: 2.1
Name: robotframework-metrics
Version: 3.7.0
Summary: Custom report for robot framework
Home-page: https://github.com/adiralashiva8/robotframework-metrics
Author: Shiva Prasad Adirala
Author-email: adiralashiva8@gmail.com
License: MIT
Keywords: robotframework report
Platform: UNKNOWN
Classifier: Framework :: Robot Framework
Classifier: Programming Language :: Python
Classifier: Topic :: Software Development :: Testing
License-File: LICENSE
Requires-Dist: robotframework
Requires-Dist: jinja2
Requires-Dist: pandas
